pyMALv2/__init__.py
pyMALv2/auth/__init__.py
pyMALv2/auth/authorization.py
pyMALv2/auth/oauth.py
pyMALv2/constants/__init__.py
pyMALv2/constants/mal_endpoints.py
pyMALv2/enums/__init__.py
pyMALv2/enums/entry_types.py
pyMALv2/exceptions/AnimeNotFound.py
pyMALv2/exceptions/AuthorizationFailed.py
pyMALv2/exceptions/InvalidAuthorizationCodeError.py
pyMALv2/exceptions/MangaNotFound.py
pyMALv2/exceptions/__init__.py
pyMALv2/models/__init__.py
pyMALv2/models/alternative_titles.py
pyMALv2/models/anime.py
pyMALv2/models/anime_my_list_status.py
pyMALv2/models/anime_recommendation.py
pyMALv2/models/author.py
pyMALv2/models/authors.py
pyMALv2/models/broadcast.py
pyMALv2/models/genre.py
pyMALv2/models/manga.py
pyMALv2/models/manga_my_list_status.py
pyMALv2/models/manga_recommendation.py
pyMALv2/models/picture.py
pyMALv2/models/related_anime.py
pyMALv2/models/related_manga.py
pyMALv2/models/serialization.py
pyMALv2/models/start_season.py
pyMALv2/models/statistics.py
pyMALv2/models/status.py
pyMALv2/models/user_anime_list_entry.py
pyMALv2/models/user_manga_list_entry.py
pyMALv2/models/utils.py
pyMALv2/services/__init__.py
pyMALv2/services/base.py
pyMALv2/services/list_base.py
pyMALv2/services/anime_service/__init__.py
pyMALv2/services/anime_service/anime_service.py
pyMALv2/services/manga_service/__init__.py
pyMALv2/services/manga_service/manga_service.py
pyMALv2/services/user_service/__init__.py
pyMALv2/services/user_service/anime_list_entry.py
pyMALv2/services/user_service/manga_list_entry.py
pyMALv2/services/user_service/user_anime_list.py
pyMALv2/services/user_service/user_manga_list.py
pyMALv2/services/user_service/user_service.py
pyMALv2-0.0.3.dist-info/LICENSE
pyMALv2-0.0.3.dist-info/METADATA
pyMALv2-0.0.3.dist-info/WHEEL
pyMALv2-0.0.3.dist-info/top_level.txt
pyMALv2-0.0.3.dist-info/RECORD
