Metadata-Version: 2.1
Name: pyMALv2
Version: 0.0.3
Summary: Python MyAnimeList v2 API wrapper.
Home-page: https://github.com/mclarence/pyMALv2
Author: Clarence
Author-email: public@cm0.dev
License: MIT
Keywords: python,myanimelist,api,wrapper,v2
Classifier: Development Status :: 3 - Alpha
Classifier: Intended Audience :: Developers
Classifier: License :: OSI Approved :: MIT License
Classifier: Programming Language :: Python :: 3.7
Classifier: Programming Language :: Python :: 3.8
Classifier: Topic :: Software Development :: Libraries :: Python Modules
License-File: LICENSE
